TM/__init__.py
TM/setup.py
TM/test_function.py
TradeMaster_try/__init__.py
TradeMaster_try/setup.py
TradeMaster_try/test_function.py
TradeMaster_try-0.0.6.dist-info/METADATA
TradeMaster_try-0.0.6.dist-info/WHEEL
TradeMaster_try-0.0.6.dist-info/top_level.txt
TradeMaster_try-0.0.6.dist-info/RECORD
