Metadata-Version: 2.1
Name: TradeMaster-try
Version: 0.0.6
Summary: TradeMaster - A platform for algorithmic trading
Home-page: https://github.com/TradeMaster-NTU/TradeMaster
Author: NTU_trademaster
Author-email: TradeMaster.NTU@gmail.com
License: UNKNOWN
Platform: UNKNOWN
Classifier: Programming Language :: Python :: 3
Classifier: License :: OSI Approved :: MIT License
Classifier: Operating System :: OS Independent
Requires-Dist: Flask
Requires-Dist: Flask-Cors
Requires-Dist: mmcv
Requires-Dist: prettytable
Requires-Dist: plotly
Requires-Dist: psutil
Requires-Dist: scipy
Requires-Dist: spacy
Requires-Dist: sqlalchemy
Requires-Dist: pandas
Requires-Dist: iopath
Requires-Dist: yfinance
Requires-Dist: matplotlib
Requires-Dist: statsmodels
Requires-Dist: scikit-learn
Requires-Dist: tslearn
Requires-Dist: jupyter
Requires-Dist: celery
Requires-Dist: pika
